jira_assistant_skills_lib/__init__.py
jira_assistant_skills_lib/adf_helper.py
jira_assistant_skills_lib/autocomplete_cache.py
jira_assistant_skills_lib/automation_client.py
jira_assistant_skills_lib/batch_processor.py
jira_assistant_skills_lib/cache.py
jira_assistant_skills_lib/config_manager.py
jira_assistant_skills_lib/credential_manager.py
jira_assistant_skills_lib/error_handler.py
jira_assistant_skills_lib/formatters.py
jira_assistant_skills_lib/jira_client.py
jira_assistant_skills_lib/jsm_utils.py
jira_assistant_skills_lib/mock_responses.py
jira_assistant_skills_lib/permission_helpers.py
jira_assistant_skills_lib/project_context.py
jira_assistant_skills_lib/request_batcher.py
jira_assistant_skills_lib/time_utils.py
jira_assistant_skills_lib/transition_helpers.py
jira_assistant_skills_lib/user_helpers.py
jira_assistant_skills_lib/validators.py
jira_assistant_skills_lib/mock/__init__.py
jira_assistant_skills_lib/mock/base.py
jira_assistant_skills_lib/mock/clients.py
jira_assistant_skills_lib/mock/mixins/__init__.py
jira_assistant_skills_lib/mock/mixins/admin.py
jira_assistant_skills_lib/mock/mixins/agile.py
jira_assistant_skills_lib/mock/mixins/collaborate.py
jira_assistant_skills_lib/mock/mixins/dev.py
jira_assistant_skills_lib/mock/mixins/fields.py
jira_assistant_skills_lib/mock/mixins/jsm.py
jira_assistant_skills_lib/mock/mixins/relationships.py
jira_assistant_skills_lib/mock/mixins/search.py
jira_assistant_skills_lib/mock/mixins/time.py
jira_assistant_skills_lib-0.2.4.dist-info/METADATA
jira_assistant_skills_lib-0.2.4.dist-info/WHEEL
jira_assistant_skills_lib-0.2.4.dist-info/licenses/LICENSE
jira_assistant_skills_lib-0.2.4.dist-info/RECORD
