Metadata-Version: 2.4
Name: jira-assistant-skills-lib
Version: 0.2.4
Summary: Shared library for JIRA Assistant Skills - HTTP client, configuration management, error handling, and utilities for JIRA REST API automation
Project-URL: Homepage, https://github.com/grandcamel/jira-assistant-skills-lib
Project-URL: Repository, https://github.com/grandcamel/jira-assistant-skills-lib
Project-URL: Issues, https://github.com/grandcamel/jira-assistant-skills-lib/issues
Project-URL: Changelog, https://github.com/grandcamel/jira-assistant-skills-lib/blob/main/CHANGELOG.md
Author-email: Jason Krueger <grandcamel@gmail.com>
License-Expression: MIT
License-File: LICENSE
Keywords: api,assistant,atlassian,automation,claude,jira,rest,skills
Classifier: Development Status :: 4 - Beta
Classifier: Intended Audience :: Developers
Classifier: License :: OSI Approved :: MIT License
Classifier: Operating System :: OS Independent
Classifier: Programming Language :: Python :: 3
Classifier: Programming Language :: Python :: 3.9
Classifier: Programming Language :: Python :: 3.10
Classifier: Programming Language :: Python :: 3.11
Classifier: Programming Language :: Python :: 3.12
Classifier: Topic :: Office/Business :: Groupware
Classifier: Topic :: Software Development :: Libraries :: Python Modules
Requires-Python: >=3.9
Requires-Dist: assistant-skills-lib>=0.2.1
Requires-Dist: colorama>=0.4.6
Requires-Dist: python-dotenv>=1.0.0
Requires-Dist: requests>=2.28.0
Requires-Dist: tabulate>=0.9.0
Requires-Dist: tqdm>=4.66.0
Provides-Extra: dev
Requires-Dist: black>=23.0.0; extra == 'dev'
Requires-Dist: isort>=5.12.0; extra == 'dev'
Requires-Dist: mypy>=1.0.0; extra == 'dev'
Requires-Dist: pytest-cov>=4.0.0; extra == 'dev'
Requires-Dist: pytest>=7.0.0; extra == 'dev'
Requires-Dist: responses>=0.24.0; extra == 'dev'
Requires-Dist: types-requests>=2.28.0; extra == 'dev'
Requires-Dist: types-tabulate>=0.9.0; extra == 'dev'
Provides-Extra: keyring
Requires-Dist: keyring>=24.0.0; extra == 'keyring'
